verylittlewire/__init__.py
verylittlewire/device.py
verylittlewire/py.typed
verylittlewire-0.4.0.dist-info/LICENSE
verylittlewire-0.4.0.dist-info/WHEEL
verylittlewire-0.4.0.dist-info/METADATA
verylittlewire-0.4.0.dist-info/RECORD
