Metadata-Version: 2.1
Name: verylittlewire
Version: 0.4.0
Summary: The Little Wire Python library provides an interface to the Little Wire USB Multi-Tool developed by Ihsan Kehribar.
Home-page: https://github.com/tiacsys/verylittlewire
License: MIT
Author: Stephan Linz
Author-email: linz@li-pro.net
Requires-Python: >=3.7,<4.0
Classifier: Development Status :: 2 - Pre-Alpha
Classifier: Intended Audience :: Developers
Classifier: License :: OSI Approved :: MIT License
Classifier: Natural Language :: English
Classifier: Operating System :: OS Independent
Classifier: Programming Language :: Python :: 3
Classifier: Programming Language :: Python :: 3.7
Classifier: Programming Language :: Python :: 3.8
Classifier: Programming Language :: Python :: 3.9
Classifier: Programming Language :: Python :: 3.10
Classifier: Programming Language :: Python :: 3.11
Classifier: Topic :: Software Development :: Libraries
Provides-Extra: docs
Requires-Dist: Sphinx (>=5.0,<6.0); extra == "docs"
Requires-Dist: myst-parser (>=0.18,<0.19); extra == "docs"
Requires-Dist: pyusb (>=1.2.1,<2.0.0)
Requires-Dist: sphinx-rtd-theme (>=1.0,<2.0); extra == "docs"
Project-URL: Bug Tracker, https://github.com/tiacsys/verylittlewire/issues
Project-URL: Changelog, https://github.com/tiacsys/verylittlewire/blob/main/CHANGELOG.md
Project-URL: Documentation, https://verylittlewire.readthedocs.io
Project-URL: Repository, https://github.com/tiacsys/verylittlewire
